ingot_mysql/__init__.py
ingot_mysql/bootstrap/__init__.py
ingot_mysql/bootstrap/base.py
ingot_mysql/bootstrap/scaffolding/__init__.py
ingot_mysql/scripts/__init__.py
ingot_mysql/scripts/ingot_mysql.py
ingot_mysql/tests/__init__.py
ingot_mysql/tests/functionals/__init__.py
ingot_mysql/tests/units/__init__.py
ingot_mysql/tests/units/bootstrap/__init__.py
ingot_mysql/tests/units/bootstrap/test_base.py
ingot_mysql/tests/units/scripts/__init__.py
ingot_mysql/tests/units/scripts/test_ingot_mysql.py
ingot_mysql-0.1.0.dist-info/LICENSE
ingot_mysql-0.1.0.dist-info/METADATA
ingot_mysql-0.1.0.dist-info/WHEEL
ingot_mysql-0.1.0.dist-info/entry_points.txt
ingot_mysql-0.1.0.dist-info/top_level.txt
ingot_mysql-0.1.0.dist-info/RECORD
